mett_dataportal/__init__.py
mett_dataportal/client.py
mett_dataportal/config.py
mett_dataportal/constants.py
mett_dataportal/exceptions.py
mett_dataportal/request_utils.py
mett_dataportal/utils.py
mett_dataportal/version.py
mett_dataportal/cli/__init__.py
mett_dataportal/cli/main.py
mett_dataportal/cli/other.py
mett_dataportal/cli/output.py
mett_dataportal/cli/utils.py
mett_dataportal/cli/core/__init__.py
mett_dataportal/cli/core/genes.py
mett_dataportal/cli/core/genomes.py
mett_dataportal/cli/core/species.py
mett_dataportal/cli/core/system.py
mett_dataportal/cli/experimental/__init__.py
mett_dataportal/cli/experimental/drugs.py
mett_dataportal/cli/experimental/essentiality.py
mett_dataportal/cli/experimental/fitness.py
mett_dataportal/cli/experimental/mutant_growth.py
mett_dataportal/cli/experimental/operons.py
mett_dataportal/cli/experimental/orthologs.py
mett_dataportal/cli/experimental/proteomics.py
mett_dataportal/cli/experimental/reactions.py
mett_dataportal/cli/interactions/__init__.py
mett_dataportal/cli/interactions/ppi.py
mett_dataportal/cli/interactions/ttp.py
mett_dataportal/models/__init__.py
mett_dataportal_sdk/__init__.py
mett_dataportal_sdk/api_client.py
mett_dataportal_sdk/api_response.py
mett_dataportal_sdk/configuration.py
mett_dataportal_sdk/exceptions.py
mett_dataportal_sdk/py.typed
mett_dataportal_sdk/rest.py
mett_dataportal_sdk/api/__init__.py
mett_dataportal_sdk/api/drugs_api.py
mett_dataportal_sdk/api/essentiality_api.py
mett_dataportal_sdk/api/fitness_api.py
mett_dataportal_sdk/api/gene_fitness_correlations_api.py
mett_dataportal_sdk/api/genes_api.py
mett_dataportal_sdk/api/genomes_api.py
mett_dataportal_sdk/api/mutant_growth_api.py
mett_dataportal_sdk/api/operons_api.py
mett_dataportal_sdk/api/orthologs_api.py
mett_dataportal_sdk/api/pooled_ttp_interactions_api.py
mett_dataportal_sdk/api/protein_protein_interactions_api.py
mett_dataportal_sdk/api/proteomics_api.py
mett_dataportal_sdk/api/py_hmmer_results_api.py
mett_dataportal-0.1.1.dist-info/METADATA
mett_dataportal-0.1.1.dist-info/WHEEL
mett_dataportal-0.1.1.dist-info/entry_points.txt
mett_dataportal-0.1.1.dist-info/top_level.txt
mett_dataportal-0.1.1.dist-info/RECORD
