Metadata-Version: 2.4
Name: mett-dataportal
Version: 0.1.1
Summary: Python client and CLI for the METT Data Portal API
Author-email: METT Data Portal <vikasg@ebi.ac.uk>
License: MIT
Keywords: microbiome,genomics,api,cli
Classifier: Development Status :: 3 - Alpha
Classifier: Intended Audience :: Science/Research
Classifier: License :: OSI Approved :: MIT License
Classifier: Programming Language :: Python :: 3
Classifier: Programming Language :: Python :: 3.10
Classifier: Programming Language :: Python :: 3.11
Classifier: Programming Language :: Python :: 3.12
Classifier: Topic :: Scientific/Engineering :: Bio-Informatics
Requires-Python: >=3.10
Requires-Dist: pydantic>=2.5
Requires-Dist: typer>=0.12
Requires-Dist: click>=8.1
Requires-Dist: rich>=13.7
Requires-Dist: requests>=2.31.0
Requires-Dist: urllib3<3,>=1.26
Requires-Dist: python-dateutil>=2.8.2
Requires-Dist: typing_extensions>=4.7.0
Requires-Dist: tomli>=2.0; python_version < "3.11"
Provides-Extra: dev
Requires-Dist: pytest>=7.4; extra == "dev"
Requires-Dist: pytest-mock>=3.11; extra == "dev"
Requires-Dist: ruff>=0.5; extra == "dev"
Requires-Dist: pre-commit>=3.5; extra == "dev"
Requires-Dist: build>=1; extra == "dev"
Requires-Dist: twine>=5; extra == "dev"
